qface_qtcpp-1.1.dist-info/DESCRIPTION.rst
qface_qtcpp-1.1.dist-info/METADATA
qface_qtcpp-1.1.dist-info/RECORD
qface_qtcpp-1.1.dist-info/WHEEL
qface_qtcpp-1.1.dist-info/entry_points.txt
qface_qtcpp-1.1.dist-info/metadata.json
qface_qtcpp-1.1.dist-info/top_level.txt
qtcpp/__init__.py
qtcpp/qtcpp.py
qtcpp/templates/CMakeLists.txt
qtcpp/templates/__init__.py
qtcpp/templates/interface.cpp
qtcpp/templates/interface.h
qtcpp/templates/plugin.cpp
qtcpp/templates/plugin.h
qtcpp/templates/plugin.pro
qtcpp/templates/qmake.conf
qtcpp/templates/qmldir
qtcpp/templates/docs/__init__.py
qtcpp/templates/docs/docs.pri
qtcpp/templates/docs/plugin-online.qdocconf
qtcpp/templates/docs/plugin-project.qdocconf
qtcpp/templates/docs/plugin.qdocconf
qtcpp/templates/generated/__init__.py
qtcpp/templates/generated/abstractinterface.cpp
qtcpp/templates/generated/abstractinterface.h
qtcpp/templates/generated/generated.pri
qtcpp/templates/generated/module.cpp
qtcpp/templates/generated/module.h
qtcpp/templates/generated/struct.cpp
qtcpp/templates/generated/struct.h
qtcpp/templates/generated/structmodel.cpp
qtcpp/templates/generated/structmodel.h
qtcpp/templates/generated/variantmodel.cpp
qtcpp/templates/generated/variantmodel.h
