Metadata-Version: 2.0
Name: qface-qtcpp
Version: 1.1
Summary: Qt CPP generator based on the QFace library
Home-page: https://github.com/Pelagicore/qface-qtcpp
Author: jryannel
Author-email: juergen@ryannel.org
License: MIT
Keywords: qt cpp generator
Platform: UNKNOWN
Classifier: Development Status :: 5 - Production/Stable
Classifier: Intended Audience :: Developers
Classifier: Topic :: Software Development :: Code Generators
Classifier: License :: OSI Approved :: MIT License
Classifier: Programming Language :: Python :: 3
Requires-Dist: qface (>=1.3.1)
